unlzw3/__init__.py
unlzw3/tests/__init__.py
unlzw3/tests/test_mod.py
unlzw3-0.2.2.dist-info/LICENSE.txt
unlzw3-0.2.2.dist-info/METADATA
unlzw3-0.2.2.dist-info/WHEEL
unlzw3-0.2.2.dist-info/top_level.txt
unlzw3-0.2.2.dist-info/RECORD
