Metadata-Version: 2.1
Name: unlzw3
Version: 0.2.2
Summary: Pure Python decompression module for .Z files compressed using Unix compress utility
Author-email: Brandon Owen <brandon.owen@hotmail.com>
Maintainer-email: Tom Kralidis <tomkralidis@gmail.com>
Keywords: lzw
Classifier: Development Status :: 4 - Beta
Classifier: Environment :: Console
Classifier: License :: OSI Approved :: MIT License
Classifier: Operating System :: OS Independent
Classifier: Programming Language :: Python :: 3
Classifier: Topic :: System :: Archiving :: Compression
Classifier: Topic :: Utilities
Requires-Python: >=3.7
License-File: LICENSE.txt
Provides-Extra: lint
Requires-Dist: flake8 ; extra == 'lint'
Requires-Dist: flake8-bugbear ; extra == 'lint'
Requires-Dist: flake8-builtins ; extra == 'lint'
Requires-Dist: flake8-blind-except ; extra == 'lint'
Requires-Dist: mypy ; extra == 'lint'
Provides-Extra: tests
Requires-Dist: pytest ; extra == 'tests'
